pluploaderng/__init__.py
pluploaderng/__main__.py
pluploaderng/confluence/__init__.py
pluploaderng/confluence/jobs/__init__.py
pluploaderng/confluence/jobs/jobs.py
pluploaderng/job.py
pluploaderng/license.py
pluploaderng/main.py
pluploaderng/mpac/__init__.py
pluploaderng/mpac/download.py
pluploaderng/mpac/exceptions.py
pluploaderng/mpac/rest.py
pluploaderng/mpac/scraper.py
pluploaderng/safemode.py
pluploaderng/upm/__init__.py
pluploaderng/upm/exceptions.py
pluploaderng/upm/upmapi.py
pluploaderng/upm/upmcloudapi.py
pluploaderng/util/__init__.py
pluploaderng/util/atlassian_jar.py
pluploaderng/util/browser.py
pluploaderng/util/pathutil.py
pluploaderng-0.9.2.dist-info/LICENSE
pluploaderng-0.9.2.dist-info/METADATA
pluploaderng-0.9.2.dist-info/WHEEL
pluploaderng-0.9.2.dist-info/entry_points.txt
pluploaderng-0.9.2.dist-info/RECORD
